nice_colorsys/__init__.py
nice_colorsys/custom_space.py
nice_colorsys/example.py
nice_colorsys/hsluv.py
nice_colorsys/nice_colorsys.py
nice_colorsys/rgb255.py
nice_colorsys-0.2.0.dist-info/licenses/LICENSE
nice_colorsys-0.2.0.dist-info/METADATA
nice_colorsys-0.2.0.dist-info/WHEEL
nice_colorsys-0.2.0.dist-info/top_level.txt
nice_colorsys-0.2.0.dist-info/RECORD
