Metadata-Version: 2.4
Name: nice_colorsys
Version: 0.2.0
Summary: A very small library that may offer a nicer way of working with color systems.
Author-email: Andrew Tapia <andrew.tapia@uky.edu>
Project-URL: Homepage, https://github.com/actapia/nice_colorsys
Project-URL: Bug Tracker, https://github.com/actapia/nice_colorsys
Classifier: Programming Language :: Python :: 3
Classifier: License :: OSI Approved :: MIT License
Classifier: Operating System :: OS Independent
Requires-Python: >=3.11
License-File: LICENSE
Dynamic: license-file
